charmcraft/__init__.py
charmcraft/__main__.py
charmcraft/_version.py
charmcraft/charm_builder.py
charmcraft/const.py
charmcraft/dispatch.py
charmcraft/env.py
charmcraft/errors.py
charmcraft/instrum.py
charmcraft/jujuignore.py
charmcraft/linters.py
charmcraft/preprocess.py
charmcraft/snap.py
charmcraft/application/__init__.py
charmcraft/application/main.py
charmcraft/application/commands/__init__.py
charmcraft/application/commands/analyse.py
charmcraft/application/commands/base.py
charmcraft/application/commands/extensions.py
charmcraft/application/commands/init.py
charmcraft/application/commands/lifecycle.py
charmcraft/application/commands/remote.py
charmcraft/application/commands/store.py
charmcraft/application/commands/version.py
charmcraft/extensions/__init__.py
charmcraft/extensions/_utils.py
charmcraft/extensions/app.py
charmcraft/extensions/extension.py
charmcraft/extensions/registry.py
charmcraft/models/__init__.py
charmcraft/models/actions.py
charmcraft/models/basic.py
charmcraft/models/charmcraft.py
charmcraft/models/config.py
charmcraft/models/lint.py
charmcraft/models/manifest.py
charmcraft/models/metadata.py
charmcraft/models/project.py
charmcraft/parts/__init__.py
charmcraft/parts/lifecycle.py
charmcraft/parts/plugins/__init__.py
charmcraft/parts/plugins/_charm.py
charmcraft/parts/plugins/_poetry.py
charmcraft/parts/plugins/_python.py
charmcraft/parts/plugins/_reactive.py
charmcraft/parts/plugins/_uv.py
charmcraft/parts/plugins/charm-constraints.txt
charmcraft/services/__init__.py
charmcraft/services/analysis.py
charmcraft/services/buildplan.py
charmcraft/services/charmlibs.py
charmcraft/services/image.py
charmcraft/services/lifecycle.py
charmcraft/services/package.py
charmcraft/services/project.py
charmcraft/services/provider.py
charmcraft/services/remotebuild.py
charmcraft/services/store.py
charmcraft/store/__init__.py
charmcraft/store/client.py
charmcraft/store/models.py
charmcraft/store/store.py
charmcraft/templates/charmlibs/new_library.py.j2
charmcraft-4.1.0.dist-info/licenses/LICENSE
charmcraft-4.1.0.dist-info/METADATA
charmcraft-4.1.0.dist-info/WHEEL
charmcraft-4.1.0.dist-info/entry_points.txt
charmcraft-4.1.0.dist-info/top_level.txt
charmcraft-4.1.0.dist-info/RECORD
