Metadata-Version: 2.4
Name: charmcraft
Version: 4.1.0
Summary: The main tool to build, upload, and develop in general the Juju charms.
License-Expression: Apache-2.0
Classifier: Development Status :: 5 - Production/Stable
Classifier: Environment :: Console
Classifier: Intended Audience :: Developers
Classifier: Operating System :: POSIX :: Linux
Classifier: Programming Language :: Python :: 3
Classifier: Programming Language :: Python :: 3.10
Classifier: Programming Language :: Python :: 3.12
Requires-Python: >=3.10
License-File: LICENSE
Requires-Dist: craft-application~=6.0
Requires-Dist: craft-cli>=2.15.0
Requires-Dist: craft-grammar>=2.0.0
Requires-Dist: craft-parts~=2.20
Requires-Dist: craft-providers~=3.1
Requires-Dist: craft-platforms~=0.10
Requires-Dist: craft-store~=3.2
Requires-Dist: distro>=1.7.0
Requires-Dist: docker>=7.0.0
Requires-Dist: humanize>=2.6.0
Requires-Dist: jsonschema~=4.0
Requires-Dist: jinja2
Requires-Dist: pydantic~=2.0
Requires-Dist: python-dateutil
Requires-Dist: pyyaml
Requires-Dist: requests
Requires-Dist: requests-toolbelt
Requires-Dist: snap-helpers
Requires-Dist: tabulate
Requires-Dist: pip>=24.2
Dynamic: license-file
